COPYRIGHT.txt
LICENSE.txt
MANIFEST.in
bootstrap.py
buildout.cfg
setup.py
docs/HISTORY.txt
src/megrok/__init__.py
src/megrok.z3cform.base.egg-info/PKG-INFO
src/megrok.z3cform.base.egg-info/SOURCES.txt
src/megrok.z3cform.base.egg-info/dependency_links.txt
src/megrok.z3cform.base.egg-info/namespace_packages.txt
src/megrok.z3cform.base.egg-info/not-zip-safe
src/megrok.z3cform.base.egg-info/requires.txt
src/megrok.z3cform.base.egg-info/top_level.txt
src/megrok/z3cform/__init__.py
src/megrok/z3cform/base/README.txt
src/megrok/z3cform/base/__init__.py
src/megrok/z3cform/base/components.py
src/megrok/z3cform/base/configure.zcml
src/megrok/z3cform/base/declarations.py
src/megrok/z3cform/base/default_form_layer.zcml
src/megrok/z3cform/base/directives.py
src/megrok/z3cform/base/handlers.py
src/megrok/z3cform/base/interfaces.py
src/megrok/z3cform/base/meta.py
src/megrok/z3cform/base/meta.zcml
src/megrok/z3cform/base/utils.py
src/megrok/z3cform/base/tests/__init__.py
src/megrok/z3cform/base/tests/ftesting.zcml
src/megrok/z3cform/base/tests/test_button.py
src/megrok/z3cform/base/tests/test_declarations.py
src/megrok/z3cform/base/tests/test_field.py
src/megrok/z3cform/base/tests/test_layout.py
src/megrok/z3cform/base/tests/test_readme.py
src/megrok/z3cform/base/tests/test_render.py
src/megrok/z3cform/base/tests/test_utils.py
src/megrok/z3cform/base/tests/test_widgettemplate.py
src/megrok/z3cform/base/tests/layout/__init__.py
src/megrok/z3cform/base/tests/layout/basic.py
src/megrok/z3cform/base/tests/layout/basic_templates/basicdisplay.pt
src/megrok/z3cform/base/tests/layout/basic_templates/basicform.pt
src/megrok/z3cform/base/tests/templates/custom_int.pt
src/megrok/z3cform/base/tests/templates/custom_string.pt
src/megrok/z3cform/base/tests/templates/custom_text.pt
src/megrok/z3cform/base/tests/templates/new_string.pt
src/megrok/z3cform/base/tests/test_layout_templates/mylayout.pt
src/megrok/z3cform/base/tests/test_widgettemplate_templates/mylayout.pt