Metadata-Version: 1.0
Name: megrok.z3cform.base
Version: 0.4
Summary: megrok extension for z3cform
Home-page: UNKNOWN
Author: Souheil Chelfouh
Author-email: trollfot@gmail.com
License: ZPL 2.1
Keywords: Grok Form
Platform: UNKNOWN
Classifier: Programming Language :: Python
Classifier: Topic :: Software Development :: Libraries :: Python Modules
Classifier: License :: OSI Approved :: Zope Public License
